cubicweb_link/__init__.py
cubicweb_link/__pkginfo__.py
cubicweb_link/entities.py
cubicweb_link/hooks.py
cubicweb_link/schema.py
cubicweb_link/uiprops.py
cubicweb_link/views.py
cubicweb_link/data/icon_link.gif
cubicweb_link/i18n/en.po
cubicweb_link/i18n/fr.po
cubicweb_link/migration/1.7.0_Any.py
cubicweb_link/migration/postcreate.py
cubicweb_link-2.1.0.dist-info/METADATA
cubicweb_link-2.1.0.dist-info/WHEEL
cubicweb_link-2.1.0.dist-info/entry_points.txt
cubicweb_link-2.1.0.dist-info/top_level.txt
cubicweb_link-2.1.0.dist-info/RECORD
